LICENSE
MANIFEST.in
README.md
requirements-cli.txt
requirements.txt
setup.cfg
setup.py
haipproxy/__init__.py
haipproxy/_version.py
haipproxy/exceptions.py
haipproxy/logger.py
haipproxy.egg-info/PKG-INFO
haipproxy.egg-info/SOURCES.txt
haipproxy.egg-info/dependency_links.txt
haipproxy.egg-info/requires.txt
haipproxy.egg-info/top_level.txt
haipproxy/client/__init__.py
haipproxy/client/core.py
haipproxy/client/py_cli.py
haipproxy/client/scrapy_middleware.py
haipproxy/client/squid.py
haipproxy/config/__init__.py
haipproxy/config/rules.py
haipproxy/config/settings.py
haipproxy/utils/__init__.py
haipproxy/utils/err_trace.py
haipproxy/utils/functools.py
haipproxy/utils/redis_util.py