Metadata-Version: 2.1
Name: haipproxy
Version: 0.11.6
Summary: High aviariable proxy pool client for crawlers.
Home-page: https://github.com/SpiderClub/haipproxy
Author: Resolvewang
Author-email: resolvewang@foxmail.com
License: MIT
Keywords: proxy,client,haipproxy
Platform: UNKNOWN
Classifier: Intended Audience :: Developers
Classifier: License :: OSI Approved :: MIT License
Classifier: Natural Language :: English
Classifier: Programming Language :: Python :: 3.4
Classifier: Programming Language :: Python :: 3.5
Classifier: Programming Language :: Python :: 3.6
Requires-Python: >=3.4.0
